odooconf/src/odooconf/__init__.py
odooconf/src/odooconf/main.py
odooconf/tests/__init__.py
odooconf-0.1.6.dist-info/METADATA
odooconf-0.1.6.dist-info/WHEEL
odooconf-0.1.6.dist-info/entry_points.txt
odooconf-0.1.6.dist-info/licenses/LICENSE
odooconf-0.1.6.dist-info/RECORD
