Metadata-Version: 2.4
Name: odooconf
Version: 0.1.6
Summary: CLI tool for managing and optimizing Odoo configurations (`odoo.conf`)
License: GNU/GPLV3
License-File: LICENSE
Keywords: odoo,config,cli,configuration,tool
Author: Alitux
Author-email: alitux@disroot.org
Requires-Python: >=3.9
Classifier: Programming Language :: Python :: 3
Classifier: Programming Language :: Python :: 3.9
Classifier: Programming Language :: Python :: 3.10
Classifier: Programming Language :: Python :: 3.11
Classifier: License :: OSI Approved :: GNU General Public License v3 (GPLv3)
Classifier: Operating System :: OS Independent
Classifier: Development Status :: 3 - Alpha
Classifier: Topic :: Software Development :: Build Tools
Classifier: Topic :: Utilities
Requires-Dist: passlib (>=1.7.4,<2.0.0)
Requires-Dist: psutil (>=7.0.0,<8.0.0)
Requires-Dist: typer (>=0.15.2,<0.16.0)
Requires-Dist: watchdog (>=6.0.0,<7.0.0)
Project-URL: Bug Tracker, https://github.com/Alitux/odooconf/issues
Project-URL: Homepage, https://github.com/Alitux/odooconf
